MANIFEST.in
README.md
setup.py
pixelhouse/__init__.py
pixelhouse/_version.py
pixelhouse/animation.py
pixelhouse/artist.py
pixelhouse/canvas.py
pixelhouse/io.py
pixelhouse/primitives.py
pixelhouse.egg-info/PKG-INFO
pixelhouse.egg-info/SOURCES.txt
pixelhouse.egg-info/dependency_links.txt
pixelhouse.egg-info/requires.txt
pixelhouse.egg-info/top_level.txt
pixelhouse/color/__init__.py
pixelhouse/color/colors.py
pixelhouse/color/interpolation.py
pixelhouse/color/palettes.py
pixelhouse/color/named_colors/matplotlib.json
pixelhouse/color/palettes/100.json
pixelhouse/color/palettes/1000.json
pixelhouse/color/palettes/200.json
pixelhouse/color/palettes/500.json
pixelhouse/filters/__init__.py
pixelhouse/filters/instagram.py
pixelhouse/filters/simple.py
pixelhouse/filters/insta/models/1977.npz
pixelhouse/filters/insta/models/Aden.npz
pixelhouse/filters/insta/models/Amaro.npz
pixelhouse/filters/insta/models/Ashby.npz
pixelhouse/filters/insta/models/Brannan.npz
pixelhouse/filters/insta/models/Brooklyn.npz
pixelhouse/filters/insta/models/Charmes.npz
pixelhouse/filters/insta/models/Clarendon.npz
pixelhouse/filters/insta/models/Crema.npz
pixelhouse/filters/insta/models/Dogpatch.npz
pixelhouse/filters/insta/models/Earlybird.npz
pixelhouse/filters/insta/models/Gingham.npz
pixelhouse/filters/insta/models/Ginza.npz
pixelhouse/filters/insta/models/Hefe.npz
pixelhouse/filters/insta/models/Helena.npz
pixelhouse/filters/insta/models/Hudson.npz
pixelhouse/filters/insta/models/Inkwell.npz
pixelhouse/filters/insta/models/Juno.npz
pixelhouse/filters/insta/models/Kelvin.npz
pixelhouse/filters/insta/models/Lark.npz
pixelhouse/filters/insta/models/Lo-Fi.npz
pixelhouse/filters/insta/models/Ludwig.npz
pixelhouse/filters/insta/models/Mayfair.npz
pixelhouse/filters/insta/models/Melvin.npz
pixelhouse/filters/insta/models/Moon.npz
pixelhouse/filters/insta/models/Nashville.npz
pixelhouse/filters/insta/models/NeveraSleep.npz
pixelhouse/filters/insta/models/Perpetua.npz
pixelhouse/filters/insta/models/Reyes.npz
pixelhouse/filters/insta/models/Rise.npz
pixelhouse/filters/insta/models/Sierra.npz
pixelhouse/filters/insta/models/Skyline.npz
