Metadata-Version: 1.1
Name: pixelhouse
Version: 0.5.5
Summary: A minimalist drawing library for making beautiful animations in python
Home-page: https://github.com/thoppe/pixelhouse
Author: Travis Hoppe
Author-email: travis.hoppe+pixelhouse@gmail.com
License: CC-SA
Keywords: art
Platform: UNKNOWN
Classifier: Development Status :: 5 - Production/Stable
Classifier: Intended Audience :: Developers
Classifier: Intended Audience :: Science/Research
Classifier: Intended Audience :: Healthcare Industry
Classifier: Intended Audience :: Education
Classifier: Intended Audience :: Financial and Insurance Industry
Classifier: Natural Language :: English
Classifier: License :: OSI Approved :: MIT License
Classifier: Programming Language :: Python :: 3.6
